{
  "SIP": {
    "coordinates": [
      [
        45.75,
        34.966666667
      ],
      [
        45.768055556,
        34.898888889
      ],
      [
        45.813611111,
        34.788055556
      ],
      [
        45.903055556,
        34.796944444
      ],
      [
        45.906944444,
        34.747777778
      ],
      [
        45.9175,
        34.722222222
      ],
      [
        45.928333333,
        34.713611111
      ],
      [
        45.985,
        34.636666667
      ],
      [
        45.996111111,
        34.614722222
      ],
      [
        45.995555556,
        34.596111111
      ],
      [
        45.978888889,
        34.548333333
      ],
      [
        45.965555556,
        34.526666667
      ],
      [
        45.948055556,
        34.458888889
      ],
      [
        45.963333333,
        34.429166667
      ],
      [
        45.997222222,
        34.405277778
      ],
      [
        46.021388889,
        34.393611111
      ],
      [
        46.038611111,
        34.365
      ],
      [
        46.048055556,
        34.344722222
      ],
      [
        46.055,
        34.280277778
      ],
      [
        46.053333333,
        34.229722222
      ],
      [
        46.057222222,
        34.185277778
      ],
      [
        46.07,
        34.154722222
      ],
      [
        46.105,
        34.104166667
      ],
      [
        46.116388889,
        34.064722222
      ],
      [
        46.107777778,
        34.039166667
      ],
      [
        46.115555556,
        34.009166667
      ],
      [
        46.166388889,
        33.898055556
      ],
      [
        46.188055556,
        33.858333333
      ],
      [
        46.195,
        33.826666667
      ],
      [
        46.195,
        33.794722222
      ],
      [
        46.185833333,
        33.756111111
      ],
      [
        46.188333333,
        33.733055556
      ],
      [
        46.2025,
        33.691388889
      ],
      [
        46.228611111,
        33.646111111
      ],
      [
        46.228888889,
        33.628888889
      ],
      [
        46.218888889,
        33.621666667
      ],
      [
        46.202222222,
        33.629722222
      ],
      [
        46.157222222,
        33.631111111
      ],
      [
        46.134166667,
        33.615277778
      ],
      [
        46.126666667,
        33.588055556
      ],
      [
        46.040833333,
        33.526388889
      ],
      [
        45.997222222,
        33.502777778
      ],
      [
        45.983333333,
        33.483333333
      ],
      [
        45.933333333,
        33.45
      ],
      [
        45.9,
        33.1
      ],
      [
        45.816666667,
        32.783333333
      ],
      [
        45.32,
        32.936666667
      ],
      [
        44.593333333,
        32.933333333
      ],
      [
        44.425,
        33.218333333
      ],
      [
        44.283055556,
        33.767777778
      ],
      [
        44.204166667,
        34.067777778
      ],
      [
        44.372222222,
        34.347222222
      ],
      [
        44.57,
        34.64
      ],
      [
        44.8,
        34.7
      ],
      [
        44.870555556,
        34.735833333
      ],
      [
        45.383333333,
        35
      ],
      [
        45.477777778,
        35.054722222
      ],
      [
        45.546388889,
        35.097222222
      ],
      [
        45.75,
        34.966666667
      ]
    ],
    "name": "Simferopol Approach"
  },
  "SIP_R": {
    "coordinates": [
      [
        45.5,
        34.123055556
      ],
      [
        45.495277778,
        33.454166667
      ],
      [
        45.377222222,
        33.361111111
      ],
      [
        44.95,
        33.533333333
      ],
      [
        44.819722222,
        33.645833333
      ],
      [
        44.763888889,
        33.693888889
      ],
      [
        44.668611111,
        33.775833333
      ],
      [
        44.621666667,
        34.047777778
      ],
      [
        44.669166667,
        34.094444444
      ],
      [
        44.835555556,
        34.258888889
      ],
      [
        44.979166667,
        34.335277778
      ],
      [
        45.1,
        34.4
      ],
      [
        45.224722222,
        34.410555556
      ],
      [
        45.359722222,
        34.410833333
      ],
      [
        45.5,
        34.123055556
      ]
    ],
    "name": "Simferopol Radar"
  }
}
